tk_lint/__init__.py
tk_lint/cli.py
tk_lint/config/ruff.toml
tk_lint-0.1.2.dist-info/METADATA
tk_lint-0.1.2.dist-info/WHEEL
tk_lint-0.1.2.dist-info/entry_points.txt
tk_lint-0.1.2.dist-info/RECORD
