Metadata-Version: 2.1
Name: tk-lint
Version: 0.1.2
Summary: 
Author: Eslam Odeh
Author-email: eslamodeh@outlook.com
Requires-Python: >=3.9,<4.0
Classifier: Programming Language :: Python :: 3
Classifier: Programming Language :: Python :: 3.9
Classifier: Programming Language :: Python :: 3.10
Classifier: Programming Language :: Python :: 3.11
Classifier: Programming Language :: Python :: 3.12
Requires-Dist: click (>=8.1.7,<9.0.0)
Requires-Dist: ruff (<1)
Requires-Dist: toml (<1)
